CHANGES
README
README.rst
setup.py
django_visits.egg-info/PKG-INFO
django_visits.egg-info/SOURCES.txt
django_visits.egg-info/dependency_links.txt
django_visits.egg-info/requires.txt
django_visits.egg-info/top_level.txt
visits/__init__.py
visits/admin.py
visits/context_processors.py
visits/middleware.py
visits/models.py
visits/settings.py
visits/tests.py
visits/utils.py
visits/migrations/0001_initial.py
visits/migrations/0002_auto__chg_field_visit_uri.py
visits/migrations/__init__.py
visits/templatetags/__init__.py
visits/templatetags/visits_tags.py