Metadata-Version: 1.1
Name: django-visits
Version: 0.1.6
Summary: Visit counter for Django
Home-page: https://bitbucket.org/jespino/django-visits
Author: Joe Willrich Lutalo
Author-email: joewillrich@gmail.com
License: LGPL
Keywords: django,visit,counter,visitors
Platform: UNKNOWN
Classifier: Development Status :: 4 - Beta
Classifier: Environment :: Web Environment
Classifier: Framework :: Django
Classifier: Intended Audience :: Developers
Classifier: Intended Audience :: Information Technology
Classifier: Intended Audience :: System Administrators
Classifier: License :: OSI Approved :: GNU Library or Lesser General Public License (LGPL)
Classifier: Natural Language :: English
Classifier: Operating System :: OS Independent
Classifier: Programming Language :: Python
Classifier: Topic :: Internet :: Log Analysis
Classifier: Topic :: Internet :: WWW/HTTP :: Dynamic Content :: Page Counters
Classifier: Topic :: Internet :: WWW/HTTP :: WSGI :: Middleware
Classifier: Topic :: System :: Monitoring
Classifier: Topic :: Utilities
